{
  "items": [
    {
      "title": "What’s On Tap",
      "slug": "workindex",
      "postDate": "2015-02-09 20:37:32",
      "heading": "Every digital product has a story to tell. It’s our job to find it and tell it well.",
      "body": "\u003Cp\u003EWhile we were not meaning to rhyme, this statement holds true. The end goal is to connect with humans, and we use the basic principles of story to do just that. Browse our work, enjoy the visuals and discover what it takes to create something great.\u003C\/p\u003E"
    }
  ]
}
